nilauth_credit_middleware/__init__.py
nilauth_credit_middleware/api_model.py
nilauth_credit_middleware/cost_calculators.py
nilauth_credit_middleware/credit_locking_client.py
nilauth_credit_middleware/credit_locking_client_singleton.py
nilauth_credit_middleware/decorator.py
nilauth_credit_middleware/dependency.py
nilauth_credit_middleware/py.typed
nilauth_credit_middleware/user_id_extractors.py
nilauth_credit_middleware-0.1.1.dist-info/WHEEL
nilauth_credit_middleware-0.1.1.dist-info/METADATA
nilauth_credit_middleware-0.1.1.dist-info/RECORD
