Metadata-Version: 2.3
Name: nilauth-credit-middleware
Version: 0.1.1
Summary: nilauth-credit-middleware
Author: José Cabrero-Holgueras
Author-email: José Cabrero-Holgueras <jose.cabrero@nillion.com>
Requires-Dist: fastapi[standard]>=0.118.0
Requires-Dist: httpx>=0.28.1
Requires-Dist: nuc>=0.1.0
Requires-Dist: pydantic>=2.11.9
Requires-Python: >=3.12
